myquery/__init__.py
myquery/database.py
myquery/logger.py
myquery/sql_builder.py
myquery/table.py
myquery/version.py
myquery/util/__init__.py
myquery/util/database_util.py
myquery/util/sql_builder_util.py
test/__init__.py
test/test_db.py
test/test_table.py
MyQuery-0.0.6.dist-info/METADATA
MyQuery-0.0.6.dist-info/WHEEL
MyQuery-0.0.6.dist-info/top_level.txt
MyQuery-0.0.6.dist-info/zip-safe
MyQuery-0.0.6.dist-info/RECORD
