Metadata-Version: 2.1
Name: MyQuery
Version: 0.0.6
Summary: 一个MySQL快捷操作方式
Home-page: https://github.com/mouday/MyQuery
Author: Peng Shiyu
Author-email: pengshiyuyx@gmail.com
License: MIT
Keywords: aquery mysql
Platform: UNKNOWN
Classifier: Programming Language :: Python :: 3.7
Requires-Dist: mysql-connector-python (==8.0.17)
